okada/__init__.py
okada/cli.py
okada/model.py
okada/results.py
okada/utils.py
okada/core/__init__.py
okada/core/lib.py
okada/core/libnames.py
okada/core/src/finite_rectangular_source.c
okada/core/src/libokada.cp311-win_amd64.pyd
okada/core/src/okada.c
okada/core/src/point_source.c
okada/core/src/utilities.c
okada/elements/__init__.py
okada/elements/planar_source.py
okada/elements/point_source.py
okada/elements/tensile_crack.py
okada/plot/__init__.py
okada/plot/displacement.py
okada/plot/strain.py
okada/plot/stress.py
okada-0.0.1.dist-info/LICENSE
okada-0.0.1.dist-info/METADATA
okada-0.0.1.dist-info/WHEEL
okada-0.0.1.dist-info/entry_points.txt
okada-0.0.1.dist-info/top_level.txt
okada-0.0.1.dist-info/RECORD
