Metadata-Version: 2.1
Name: okada
Version: 0.0.1
Summary: A Python toolkit for evaluating analytical deformation models
Author-email: "Conor A. Bacon" <cbacon@ldeo.columbia.edu>
Maintainer-email: "Conor A. Bacon" <cbacon@ldeo.columbia.edu>
License: GPLv3
Project-URL: GitHub, https://github.com/hemmelig/OkadaPy
Project-URL: Issues, https://github.com/hemmelig/OkadaPy/issues
Keywords: array,okada,deformation,geodesy,modelling,processing
Classifier: Development Status :: 3 - Alpha
Classifier: Intended Audience :: Science/Research
Classifier: Topic :: Scientific/Engineering
Classifier: Natural Language :: English
Classifier: License :: OSI Approved :: GNU General Public License v3 (GPLv3)
Classifier: Operating System :: OS Independent
Classifier: Programming Language :: Python
Classifier: Programming Language :: Python :: 3
Classifier: Programming Language :: Python :: 3.11
Requires-Python: >=3.11
License-File: LICENSE
Requires-Dist: matplotlib
Requires-Dist: numpy
Requires-Dist: pandas
Requires-Dist: pygmt
Requires-Dist: pyproj
Provides-Extra: dev
Requires-Dist: ipython; extra == "dev"
Requires-Dist: pre-commit; extra == "dev"
Requires-Dist: ruff; extra == "dev"
Requires-Dist: coverage; extra == "dev"
Provides-Extra: docs
Requires-Dist: doc-utils<0.17; extra == "docs"
Requires-Dist: mock; extra == "docs"
Requires-Dist: Sphinx>=4.3.0; extra == "docs"
Requires-Dist: sphinx_rtd_theme>=0.5.1; extra == "docs"
